{
  "notes": [
    {
      "id": 1,
      "content": "this is it, first note ever !!",
      "createdAt": "2020-04-27T17:39:19.533Z",
      "updatedAt": "2020-04-30T13:21:29.158Z",
      "folder": "test"
    },
    {
      "id": 2,
      "content": "what do you think?\nwhen you are alone",
      "createdAt": "2020-04-28T13:30:19.533Z",
      "updatedAt": "2020-05-01T12:06:35.593Z",
      "folder": "javascript"
    },
    {
      "id": 3,
      "content": "The best thing about a boolean is even if you are wrong, you are only off by a bit, even if...\n\nWell you know right?",
      "createdAt": "2020-04-27T17:39:19.533Z",
      "updatedAt": "2020-05-01T11:54:22.872Z",
      "folder": "javascript"
    },
    {
      "id": 4,
      "content": "this is a sentence that is not that useful",
      "createdAt": "2020-04-27T16:39:19.533Z",
      "updatedAt": "",
      "folder": "test"
    }
  ]
}